py_now_playing/__init__.py
py_now_playing/media_controls.py
py_now_playing-0.1.0.dist-info/LICENSE.md
py_now_playing-0.1.0.dist-info/METADATA
py_now_playing-0.1.0.dist-info/WHEEL
py_now_playing-0.1.0.dist-info/RECORD
