Metadata-Version: 2.1
Name: py-now-playing
Version: 0.1.0
Summary: A Python Library to get the currently playing media
Author: ABUCKY0
Author-email: 81783950+ABUCKY0@users.noreply.github.com
Requires-Python: >=3.11,<4.0
Classifier: Programming Language :: Python :: 3
Classifier: Programming Language :: Python :: 3.11
Classifier: Programming Language :: Python :: 3.12
Requires-Dist: pillow (>=10.1.0,<11.0.0)
Requires-Dist: winsdk (>=1.0.0b10,<2.0.0)
